ncut_pytorch/__init__.py
ncut_pytorch/ncut.py
ncut_pytorch/color/__init__.py
ncut_pytorch/color/coloring.py
ncut_pytorch/color/mspace.py
ncut_pytorch/ncuts/__init__.py
ncut_pytorch/ncuts/ncut_click.py
ncut_pytorch/ncuts/ncut_kway.py
ncut_pytorch/ncuts/ncut_nystrom.py
ncut_pytorch/predictor/__init__.py
ncut_pytorch/predictor/dino_predictor.py
ncut_pytorch/predictor/jafar_predictor.py
ncut_pytorch/predictor/predictor.py
ncut_pytorch/predictor/vision_predictor.py
ncut_pytorch/predictor/dino/__init__.py
ncut_pytorch/predictor/dino/api.py
ncut_pytorch/predictor/dino/dinov3.py
ncut_pytorch/predictor/dino/hires_dino.py
ncut_pytorch/predictor/dino/lowres_dino.py
ncut_pytorch/predictor/dino/patch.py
ncut_pytorch/predictor/dino/transform.py
ncut_pytorch/utils/__init__.py
ncut_pytorch/utils/device.py
ncut_pytorch/utils/gamma.py
ncut_pytorch/utils/grad.py
ncut_pytorch/utils/math.py
ncut_pytorch/utils/sample.py
ncut_pytorch/utils/torch_mod.py
ncut_pytorch-2.3.3.dist-info/licenses/LICENSE
ncut_pytorch-2.3.3.dist-info/METADATA
ncut_pytorch-2.3.3.dist-info/WHEEL
ncut_pytorch-2.3.3.dist-info/top_level.txt
ncut_pytorch-2.3.3.dist-info/RECORD
