Metadata-Version: 2.4
Name: ncut_pytorch
Version: 2.3.3
Summary: Normalized Cut and Spectral Embedding
Author-email: Huzheng Yang <huze.yann@gmail.com>
License-Expression: MIT
Project-URL: Documentation, https://ncut-pytorch.readthedocs.io/
Project-URL: Github, https://github.com/huzeyann/ncut_pytorch/
Project-URL: PyPI, https://pypi.org/project/ncut_pytorch/
Classifier: Programming Language :: Python :: 3
Classifier: Operating System :: OS Independent
Classifier: Development Status :: 5 - Production/Stable
Classifier: Intended Audience :: Science/Research
Classifier: Topic :: Scientific/Engineering :: Image Processing
Classifier: Topic :: Scientific/Engineering :: Mathematics
Requires-Python: >=3
License-File: LICENSE
Requires-Dist: numpy<2.0
Requires-Dist: fpsample>=0.2.0
Requires-Dist: tqdm
Requires-Dist: pillow
Requires-Dist: opencv-python
Requires-Dist: matplotlib
Requires-Dist: umap-learn
Provides-Extra: torch
Requires-Dist: torch>=2.7.1; extra == "torch"
Requires-Dist: pytorch-lightning~=2.0; extra == "torch"
Requires-Dist: torchvision>=0.23.0; extra == "torch"
Provides-Extra: cmap
Requires-Dist: pycolormap_2d; extra == "cmap"
Requires-Dist: scikit-image; extra == "cmap"
Provides-Extra: dev
Requires-Dist: pytest>=7.0.0; extra == "dev"
Requires-Dist: pytest-cov>=4.0.0; extra == "dev"
Requires-Dist: pytest-mock>=3.10.0; extra == "dev"
Requires-Dist: tabulate; extra == "dev"
Requires-Dist: pytest-benchmark>=5.1.0; extra == "dev"
Provides-Extra: all
Requires-Dist: ncut_pytorch[cmap,dev,torch]; extra == "all"
Dynamic: license-file
